docker_compose_cleanup/__init__.py
docker_compose_cleanup/cli.py
docker_compose_cleanup/docker_compose_cleanup.py
docker_compose_cleanup-1.1.0.dist-info/DESCRIPTION.rst
docker_compose_cleanup-1.1.0.dist-info/METADATA
docker_compose_cleanup-1.1.0.dist-info/RECORD
docker_compose_cleanup-1.1.0.dist-info/WHEEL
docker_compose_cleanup-1.1.0.dist-info/entry_points.txt
docker_compose_cleanup-1.1.0.dist-info/metadata.json
docker_compose_cleanup-1.1.0.dist-info/top_level.txt
