Metadata-Version: 2.0
Name: docker-compose-cleanup
Version: 1.1.0
Summary: Helps you cleanup Docker images of multiple Docker Compose projects.
Home-page: https://github.com/rivol/docker-compose-cleanup
Author: Rivo Laks
Author-email: code@rivolaks.com
License: ISC license
Keywords: docker-compose-cleanup
Platform: UNKNOWN
Classifier: Development Status :: 4 - Beta
Classifier: Intended Audience :: Developers
Classifier: License :: OSI Approved :: ISC License (ISCL)
Classifier: Natural Language :: English
Classifier: Programming Language :: Python :: 3
Classifier: Programming Language :: Python :: 3.4
Classifier: Programming Language :: Python :: 3.5
Classifier: Programming Language :: Python :: 3.6
Requires-Dist: Click (<7,>=6.0)
Requires-Dist: colorama (<1,>=0.3.9)
Requires-Dist: docker (<3,>=2.6)
